emta/__init__.py
emta/py.typed
emta/api/__init__.py
emta/api/client.py
emta/auth/__init__.py
emta/auth/client.py
emta/core/__init__.py
emta/core/agent.py
emta/models/__init__.py
emta/models/exceptions.py
emta/models/trading.py
emta/utils/__init__.py
emta/utils/captcha.py
emta/utils/encryption.py
emta/utils/stocks.py
emta-0.5.0.dist-info/METADATA
emta-0.5.0.dist-info/WHEEL
emta-0.5.0.dist-info/licenses/LICENSE
emta-0.5.0.dist-info/RECORD
