Metadata-Version: 2.4
Name: emta
Version: 0.5.0
Summary: Easy Money Trading Agent
Author-email: zhou bo <wokspc@gmail.com>
License-Expression: MIT
License-File: LICENSE
Keywords: trade,trade api,东方财富,东财,交易,交易API,交易代理,交易机器人,自动交易,自动化交易
Requires-Python: >=3.11
Requires-Dist: cryptography>=45.0.6
Requires-Dist: ddddocr>=1.5.6
Requires-Dist: httpx>=0.28.1
Requires-Dist: loguru>=0.7.3
